rest_framework_mixins/__init__.py
rest_framework_mixins/generate.py
rest_framework_mixins/py.typed
rest_framework_mixins-1.0.0.dist-info/LICENSE
rest_framework_mixins-1.0.0.dist-info/METADATA
rest_framework_mixins-1.0.0.dist-info/WHEEL
rest_framework_mixins-1.0.0.dist-info/entry_points.txt
rest_framework_mixins-1.0.0.dist-info/RECORD
