Metadata-Version: 2.1
Name: rest_framework_mixins
Version: 1.0.0
Summary: A collection of DRF mixins combinations
Home-page: https://github.com/Qu4tro/rest_framework_mixins
License: MIT
Keywords: django,djangorestframework,drf,restframework,rest_framework,mixins
Author: Xavier Francisco
Author-email: xavier.n.francisco@gmail.com
Requires-Python: >=3.9,<4.0
Classifier: License :: OSI Approved :: MIT License
Classifier: Programming Language :: Python :: 3
Classifier: Programming Language :: Python :: 3.9
Classifier: Programming Language :: Python :: 3.10
Classifier: Programming Language :: Python :: 3.11
Classifier: Programming Language :: Python :: 3.12
Requires-Dist: django
Requires-Dist: djangorestframework
Project-URL: Repository, https://github.com/Qu4tro/rest_framework_mixins
